acp/__init__.py
acp/agent/__init__.py
acp/agent/connection.py
acp/agent/router.py
acp/client/__init__.py
acp/client/connection.py
acp/client/router.py
acp/connection.py
acp/contrib/__init__.py
acp/contrib/permissions.py
acp/contrib/session_state.py
acp/contrib/tool_calls.py
acp/core.py
acp/exceptions.py
acp/helpers.py
acp/interfaces.py
acp/meta.py
acp/py.typed
acp/router.py
acp/schema.py
acp/stdio.py
acp/task/__init__.py
acp/task/dispatcher.py
acp/task/queue.py
acp/task/sender.py
acp/task/state.py
acp/task/supervisor.py
acp/telemetry.py
acp/terminal.py
acp/transports.py
acp/utils.py
agent_client_protocol-0.7.1.dist-info/METADATA
agent_client_protocol-0.7.1.dist-info/WHEEL
agent_client_protocol-0.7.1.dist-info/entry_points.txt
agent_client_protocol-0.7.1.dist-info/licenses/LICENSE
agent_client_protocol-0.7.1.dist-info/RECORD
