Metadata-Version: 2.1
Name: agent-client-protocol
Version: 0.7.1
Summary: A Python implement of Agent Client Protocol (ACP, by Zed Industries)
Keywords: python
Author-Email: Chojan Shang <psiace@apache.org>, Frost Ming <me@frostming.com>
Classifier: Intended Audience :: Developers
Classifier: Programming Language :: Python
Classifier: Programming Language :: Python :: 3
Classifier: Programming Language :: Python :: 3.10
Classifier: Programming Language :: Python :: 3.11
Classifier: Programming Language :: Python :: 3.12
Classifier: Programming Language :: Python :: 3.13
Classifier: Programming Language :: Python :: 3.14
Classifier: Topic :: Software Development :: Libraries :: Python Modules
Project-URL: Homepage, https://agentclientprotocol.github.io/python-sdk/
Project-URL: Repository, https://github.com/agentclientprotocol/python-sdk
Project-URL: Documentation, https://agentclientprotocol.github.io/python-sdk/
Requires-Python: <3.15,>=3.10
Requires-Dist: pydantic>=2.7
Provides-Extra: logfire
Requires-Dist: logfire>=0.14; extra == "logfire"
Requires-Dist: opentelemetry-sdk>=1.28.0; extra == "logfire"
